torch_cfd/__init__.py
torch_cfd/advection.py
torch_cfd/boundaries.py
torch_cfd/finite_differences.py
torch_cfd/forcings.py
torch_cfd/fvm.py
torch_cfd/grids.py
torch_cfd/initial_conditions.py
torch_cfd/solvers.py
torch_cfd/spectral.py
torch_cfd/tensor_utils.py
torch_cfd/test_utils.py
torch_cfd/tests/__init__.py
torch_cfd/tests/test_advection.py
torch_cfd/tests/test_boundaries.py
torch_cfd/tests/test_finite_differences.py
torch_cfd/tests/test_grids.py
torch_cfd/tests/test_solvers.py
torch_cfd-0.2.6.dist-info/licenses/LICENSE
torch_cfd-0.2.6.dist-info/licenses/LICENSE-MIT
torch_cfd-0.2.6.dist-info/METADATA
torch_cfd-0.2.6.dist-info/WHEEL
torch_cfd-0.2.6.dist-info/top_level.txt
torch_cfd-0.2.6.dist-info/RECORD
